{  "schema": "btc_pulse_score_history/1.0",  "entries": [   {    "ts": 1782394283.5733743,    "utc": "2026-06-25 13:31:23 UTC",    "ticks": 1,    "settled": 29,    "scores": {     "trading_performance": 72.1,     "operation": 90.3,     "external_signals": 71.4,     "overall": 76.5,     "grades": {      "trading_performance": "C",      "operation": "A",      "external_signals": "C",      "overall": "C+"     }    }   },   {    "ts": 1782396085.3583174,    "utc": "2026-06-25 14:01:25 UTC",    "ticks": 254,    "settled": 29,    "scores": {     "trading_performance": 72.1,     "operation": 90.4,     "external_signals": 70.9,     "overall": 76.4,     "grades": {      "trading_performance": "C",      "operation": "A",      "external_signals": "C",      "overall": "C+"     }    }   },   {    "ts": 1782397888.9854777,    "utc": "2026-06-25 14:31:28 UTC",    "ticks": 260,    "settled": 29,    "scores": {     "trading_performance": 72.1,     "operation": 90.4,     "external_signals": 71.2,     "overall": 76.5,     "grades": {      "trading_performance": "C",      "operation": "A",      "external_signals": "C",      "overall": "C+"     }    }   },   {    "ts": 1782399689.819906,    "utc": "2026-06-25 15:01:29 UTC",    "ticks": 709,    "settled": 29,    "scores": {     "trading_performance": 72.1,     "operation": 90.4,     "external_signals": 70.7,     "overall": 76.3,     "grades": {      "trading_performance": "C",      "operation": "A",      "external_signals": "C",      "overall": "C+"     }    }   },   {    "ts": 1782401490.1134462,    "utc": "2026-06-25 15:31:30 UTC",    "ticks": 1159,    "settled": 29,    "scores": {     "trading_performance": 72.1,     "operation": 90.5,     "external_signals": 70.3,     "overall": 76.2,     "grades": {      "trading_performance": "C",      "operation": "A",      "external_signals": "C",      "overall": "C+"     }    }   },   {    "ts": 1782403290.1147943,    "utc": "2026-06-25 16:01:30 UTC",    "ticks": 1609,    "settled": 29,    "scores": {     "trading_performance": 72.1,     "operation": 90.5,     "external_signals": 71.3,     "overall": 76.5,     "grades": {      "trading_performance": "C",      "operation": "A",      "external_signals": "C",      "overall": "C+"     }    }   },   {    "ts": 1782405092.4354112,    "utc": "2026-06-25 16:31:32 UTC",    "ticks": 218,    "settled": 29,    "scores": {     "trading_performance": 72.1,     "operation": 90.5,     "external_signals": 70.6,     "overall": 76.3,     "grades": {      "trading_performance": "C",      "operation": "A",      "external_signals": "C",      "overall": "C+"     }    }   },   {    "ts": 1782406892.4800553,    "utc": "2026-06-25 17:01:32 UTC",    "ticks": 668,    "settled": 29,    "scores": {     "trading_performance": 72.1,     "operation": 90.5,     "external_signals": 70.0,     "overall": 76.2,     "grades": {      "trading_performance": "C",      "operation": "A",      "external_signals": "C",      "overall": "C+"     }    }   },   {    "ts": 1782407583.835737,    "utc": "2026-06-25 17:13:03 UTC",    "ticks": 113,    "settled": 30,    "scores": {     "trading_performance": 68.1,     "operation": 90.5,     "external_signals": 69.0,     "overall": 73.9,     "grades": {      "trading_performance": "D",      "operation": "A",      "external_signals": "D",      "overall": "C"     }    }   },   {    "ts": 1782407587.8123941,    "utc": "2026-06-25 17:13:07 UTC",    "ticks": 114,    "settled": 30,    "scores": {     "trading_performance": 68.1,     "operation": 75.5,     "external_signals": 69.0,     "overall": 70.2,     "grades": {      "trading_performance": "D",      "operation": "C+",      "external_signals": "D",      "overall": "C"     }    }   },   {    "ts": 1782408092.0431263,    "utc": "2026-06-25 17:21:32 UTC",    "ticks": 1,    "settled": 30,    "scores": {     "trading_performance": 68.1,     "operation": 90.5,     "external_signals": 69.0,     "overall": 73.9,     "grades": {      "trading_performance": "D",      "operation": "A",      "external_signals": "D",      "overall": "C"     }    }   },   {    "ts": 1782409084.2457685,    "utc": "2026-06-25 17:38:04 UTC",    "ticks": 249,    "settled": 31,    "scores": {     "trading_performance": 65.3,     "operation": 90.6,     "external_signals": 63.9,     "overall": 71.3,     "grades": {      "trading_performance": "D",      "operation": "A",      "external_signals": "D",      "overall": "C"     }    }   },   {    "ts": 1782410886.9389045,    "utc": "2026-06-25 18:08:06 UTC",    "ticks": 86,    "settled": 31,    "scores": {     "trading_performance": 65.3,     "operation": 90.6,     "external_signals": 63.9,     "overall": 71.3,     "grades": {      "trading_performance": "D",      "operation": "A",      "external_signals": "D",      "overall": "C"     }    }   },   {    "ts": 1782412687.2691002,    "utc": "2026-06-25 18:38:07 UTC",    "ticks": 536,    "settled": 31,    "scores": {     "trading_performance": 65.3,     "operation": 90.6,     "external_signals": 63.9,     "overall": 71.3,     "grades": {      "trading_performance": "D",      "operation": "A",      "external_signals": "D",      "overall": "C"     }    }   },   {    "ts": 1782414489.4902506,    "utc": "2026-06-25 19:08:09 UTC",    "ticks": 5,    "settled": 31,    "scores": {     "trading_performance": 65.3,     "operation": 90.6,     "external_signals": 63.9,     "overall": 71.3,     "grades": {      "trading_performance": "D",      "operation": "A",      "external_signals": "D",      "overall": "C"     }    }   },   {    "ts": 1782416289.906674,    "utc": "2026-06-25 19:38:09 UTC",    "ticks": 455,    "settled": 31,    "scores": {     "trading_performance": 65.3,     "operation": 90.6,     "external_signals": 63.9,     "overall": 71.3,     "grades": {      "trading_performance": "D",      "operation": "A",      "external_signals": "D",      "overall": "C"     }    }   },   {    "ts": 1782418093.346147,    "utc": "2026-06-25 20:08:13 UTC",    "ticks": 91,    "settled": 31,    "scores": {     "trading_performance": 65.3,     "operation": 90.6,     "external_signals": 63.9,     "overall": 71.3,     "grades": {      "trading_performance": "D",      "operation": "A",      "external_signals": "D",      "overall": "C"     }    }   },   {    "ts": 1782419893.378618,    "utc": "2026-06-25 20:38:13 UTC",    "ticks": 541,    "settled": 31,    "scores": {     "trading_performance": 65.3,     "operation": 90.6,     "external_signals": 63.9,     "overall": 71.3,     "grades": {      "trading_performance": "D",      "operation": "A",      "external_signals": "D",      "overall": "C"     }    }   },   {    "ts": 1782421693.4798412,    "utc": "2026-06-25 21:08:13 UTC",    "ticks": 991,    "settled": 31,    "scores": {     "trading_performance": 65.3,     "operation": 90.7,     "external_signals": 63.9,     "overall": 71.3,     "grades": {      "trading_performance": "D",      "operation": "A",      "external_signals": "D",      "overall": "C"     }    }   },   {    "ts": 1782423494.676693,    "utc": "2026-06-25 21:38:14 UTC",    "ticks": 84,    "settled": 31,    "scores": {     "trading_performance": 65.3,     "operation": 90.7,     "external_signals": 63.9,     "overall": 71.3,     "grades": {      "trading_performance": "D",      "operation": "A",      "external_signals": "D",      "overall": "C"     }    }   },   {    "ts": 1782425298.575516,    "utc": "2026-06-25 22:08:18 UTC",    "ticks": 112,    "settled": 31,    "scores": {     "trading_performance": 65.3,     "operation": 90.7,     "external_signals": 63.4,     "overall": 71.2,     "grades": {      "trading_performance": "D",      "operation": "A",      "external_signals": "D",      "overall": "C"     }    }   },   {    "ts": 1782425530.6195798,    "utc": "2026-06-25 22:12:10 UTC",    "ticks": 170,    "settled": 32,    "scores": {     "trading_performance": 62.6,     "operation": 90.7,     "external_signals": 59.1,     "overall": 68.8,     "grades": {      "trading_performance": "D",      "operation": "A",      "external_signals": "F",      "overall": "D"     }    }   },   {    "ts": 1782425822.984486,    "utc": "2026-06-25 22:17:02 UTC",    "ticks": 243,    "settled": 33,    "scores": {     "trading_performance": 59.8,     "operation": 90.5,     "external_signals": 55.5,     "overall": 66.4,     "grades": {      "trading_performance": "F",      "operation": "A",      "external_signals": "F",      "overall": "D"     }    }   },   {    "ts": 1782426726.645189,    "utc": "2026-06-25 22:32:06 UTC",    "ticks": 469,    "settled": 34,    "scores": {     "trading_performance": 56.9,     "operation": 90.5,     "external_signals": 52.3,     "overall": 64.2,     "grades": {      "trading_performance": "F",      "operation": "A",      "external_signals": "F",      "overall": "D"     }    }   },   {    "ts": 1782427082.6291652,    "utc": "2026-06-25 22:38:02 UTC",    "ticks": 558,    "settled": 35,    "scores": {     "trading_performance": 54.1,     "operation": 90.5,     "external_signals": 54.8,     "overall": 63.4,     "grades": {      "trading_performance": "F",      "operation": "A",      "external_signals": "F",      "overall": "D"     }    }   },   {    "ts": 1782427362.625743,    "utc": "2026-06-25 22:42:42 UTC",    "ticks": 628,    "settled": 36,    "scores": {     "trading_performance": 56.5,     "operation": 90.5,     "external_signals": 52.6,     "overall": 64.0,     "grades": {      "trading_performance": "F",      "operation": "A",      "external_signals": "F",      "overall": "D"     }    }   },   {    "ts": 1782427591.852485,    "utc": "2026-06-25 22:46:31 UTC",    "ticks": 42,    "settled": 37,    "scores": {     "trading_performance": 58.6,     "operation": 90.5,     "external_signals": 50.8,     "overall": 64.6,     "grades": {      "trading_performance": "F",      "operation": "A",      "external_signals": "F",      "overall": "D"     }    }   },   {    "ts": 1782429394.8095026,    "utc": "2026-06-25 23:16:34 UTC",    "ticks": 428,    "settled": 37,    "scores": {     "trading_performance": 58.6,     "operation": 90.6,     "external_signals": 50.8,     "overall": 64.7,     "grades": {      "trading_performance": "F",      "operation": "A",      "external_signals": "F",      "overall": "D"     }    }   },   {    "ts": 1782431198.047461,    "utc": "2026-06-25 23:46:38 UTC",    "ticks": 67,    "settled": 37,    "scores": {     "trading_performance": 58.6,     "operation": 90.6,     "external_signals": 50.8,     "overall": 64.7,     "grades": {      "trading_performance": "F",      "operation": "A",      "external_signals": "F",      "overall": "D"     }    }   },   {    "ts": 1782432165.9445107,    "utc": "2026-06-26 00:02:45 UTC",    "ticks": 309,    "settled": 38,    "scores": {     "trading_performance": 61.4,     "operation": 90.6,     "external_signals": 52.7,     "overall": 66.5,     "grades": {      "trading_performance": "D",      "operation": "A",      "external_signals": "F",      "overall": "D"     }    }   },   {    "ts": 1782432481.769714,    "utc": "2026-06-26 00:08:01 UTC",    "ticks": 388,    "settled": 39,    "scores": {     "trading_performance": 64.0,     "operation": 90.6,     "external_signals": 51.1,     "overall": 67.4,     "grades": {      "trading_performance": "D",      "operation": "A",      "external_signals": "F",      "overall": "D"     }    }   },   {    "ts": 1782432781.7568097,    "utc": "2026-06-26 00:13:01 UTC",    "ticks": 463,    "settled": 40,    "scores": {     "trading_performance": 66.3,     "operation": 90.6,     "external_signals": 51.1,     "overall": 68.6,     "grades": {      "trading_performance": "D",      "operation": "A",      "external_signals": "F",      "overall": "D"     }    }   },   {    "ts": 1782432785.739347,    "utc": "2026-06-26 00:13:05 UTC",    "ticks": 464,    "settled": 40,    "scores": {     "trading_performance": 66.3,     "operation": 75.6,     "external_signals": 51.1,     "overall": 64.8,     "grades": {      "trading_performance": "D",      "operation": "C+",      "external_signals": "F",      "overall": "D"     }    }   },   {    "ts": 1782433082.1940439,    "utc": "2026-06-26 00:18:02 UTC",    "ticks": 538,    "settled": 41,    "scores": {     "trading_performance": 69.4,     "operation": 75.6,     "external_signals": 51.1,     "overall": 66.4,     "grades": {      "trading_performance": "D",      "operation": "C+",      "external_signals": "F",      "overall": "D"     }    }   },   {    "ts": 1782433759.104493,    "utc": "2026-06-26 00:29:19 UTC",    "ticks": 1,    "settled": 41,    "scores": {     "trading_performance": 69.4,     "operation": 90.6,     "external_signals": 51.1,     "overall": 70.1,     "grades": {      "trading_performance": "D",      "operation": "A",      "external_signals": "F",      "overall": "C"     }    }   },   {    "ts": 1782434282.9716892,    "utc": "2026-06-26 00:38:02 UTC",    "ticks": 132,    "settled": 42,    "scores": {     "trading_performance": 64.0,     "operation": 90.6,     "external_signals": 48.5,     "overall": 66.8,     "grades": {      "trading_performance": "D",      "operation": "A",      "external_signals": "F",      "overall": "D"     }    }   },   {    "ts": 1782434286.9587507,    "utc": "2026-06-26 00:38:06 UTC",    "ticks": 133,    "settled": 42,    "scores": {     "trading_performance": 64.0,     "operation": 75.6,     "external_signals": 48.5,     "overall": 63.0,     "grades": {      "trading_performance": "D",      "operation": "C+",      "external_signals": "F",      "overall": "D"     }    }   },   {    "ts": 1782434583.33879,    "utc": "2026-06-26 00:43:03 UTC",    "ticks": 207,    "settled": 43,    "scores": {     "trading_performance": 66.7,     "operation": 75.6,     "external_signals": 50.4,     "overall": 64.8,     "grades": {      "trading_performance": "D",      "operation": "C+",      "external_signals": "F",      "overall": "D"     }    }   },   {    "ts": 1782436386.153305,    "utc": "2026-06-26 01:13:06 UTC",    "ticks": 657,    "settled": 43,    "scores": {     "trading_performance": 66.7,     "operation": 75.6,     "external_signals": 50.4,     "overall": 64.8,     "grades": {      "trading_performance": "D",      "operation": "C+",      "external_signals": "F",      "overall": "D"     }    }   },   {    "ts": 1782438104.660483,    "utc": "2026-06-26 01:41:44 UTC",    "ticks": 1,    "settled": 43,    "scores": {     "trading_performance": 66.7,     "operation": 90.6,     "external_signals": 50.4,     "overall": 68.6,     "grades": {      "trading_performance": "D",      "operation": "A",      "external_signals": "F",      "overall": "D"     }    }   },   {    "ts": 1782438672.0401304,    "utc": "2026-06-26 01:51:12 UTC",    "ticks": 137,    "settled": 44,    "scores": {     "trading_performance": 61.6,     "operation": 90.6,     "external_signals": 48.1,     "overall": 65.5,     "grades": {      "trading_performance": "D",      "operation": "A",      "external_signals": "F",      "overall": "D"     }    }   },   {    "ts": 1782440475.4942768,    "utc": "2026-06-26 02:21:15 UTC",    "ticks": 588,    "settled": 44,    "scores": {     "trading_performance": 61.6,     "operation": 90.6,     "external_signals": 48.1,     "overall": 65.5,     "grades": {      "trading_performance": "D",      "operation": "A",      "external_signals": "F",      "overall": "D"     }    }   },   {    "ts": 1782440583.4782422,    "utc": "2026-06-26 02:23:03 UTC",    "ticks": 615,    "settled": 45,    "scores": {     "trading_performance": 64.2,     "operation": 90.6,     "external_signals": 48.1,     "overall": 66.8,     "grades": {      "trading_performance": "D",      "operation": "A",      "external_signals": "F",      "overall": "D"     }    }   },   {    "ts": 1782440857.219829,    "utc": "2026-06-26 02:27:37 UTC",    "ticks": 1,    "settled": 46,    "scores": {     "trading_performance": 67.7,     "operation": 90.6,     "external_signals": 49.9,     "overall": 69.0,     "grades": {      "trading_performance": "D",      "operation": "A",      "external_signals": "F",      "overall": "D"     }    }   },   {    "ts": 1782442661.0948453,    "utc": "2026-06-26 02:57:41 UTC",    "ticks": 11,    "settled": 46,    "scores": {     "trading_performance": 67.7,     "operation": 90.3,     "external_signals": 49.9,     "overall": 68.9,     "grades": {      "trading_performance": "D",      "operation": "A",      "external_signals": "F",      "overall": "D"     }    }   },   {    "ts": 1782442673.2935205,    "utc": "2026-06-26 02:57:53 UTC",    "ticks": 14,    "settled": 47,    "scores": {     "trading_performance": 70.8,     "operation": 90.3,     "external_signals": 51.5,     "overall": 70.8,     "grades": {      "trading_performance": "C",      "operation": "A",      "external_signals": "F",      "overall": "C"     }    }   },   {    "ts": 1782444475.6336868,    "utc": "2026-06-26 03:27:55 UTC",    "ticks": 21,    "settled": 47,    "scores": {     "trading_performance": 70.8,     "operation": 90.2,     "external_signals": 51.5,     "overall": 70.8,     "grades": {      "trading_performance": "C",      "operation": "A",      "external_signals": "F",      "overall": "C"     }    }   },   {    "ts": 1782445631.6566234,    "utc": "2026-06-26 03:47:11 UTC",    "ticks": 310,    "settled": 48,    "scores": {     "trading_performance": 65.8,     "operation": 90.0,     "external_signals": 53.7,     "overall": 68.8,     "grades": {      "trading_performance": "D",      "operation": "A",      "external_signals": "F",      "overall": "D"     }    }   },   {    "ts": 1782447432.7866428,    "utc": "2026-06-26 04:17:12 UTC",    "ticks": 224,    "settled": 48,    "scores": {     "trading_performance": 65.8,     "operation": 90.0,     "external_signals": 53.9,     "overall": 68.9,     "grades": {      "trading_performance": "D",      "operation": "A",      "external_signals": "F",      "overall": "D"     }    }   }  ] }