{"schema": "active_learning/1.0", "paper_only": true, "active_learning_enabled": true, "random_exploration_enabled": false, "random_exploration_opened_trades": 0, "legacy_random_exploration_blocked": 51, "active_learning_candidates_considered": 720, "active_learning_candidates_selected": 720, "active_learning_shadow_selected": 720, "zero_selection_reason": null, "exploration_trades_opened": 0, "exploration_shadow_only": 213, "exploration_rejected_by_realism": 49, "exploration_rejected_by_profitability": 0, "exploration_rejected_by_budget": 0, "exploration_rejected_by_collision": 0, "exploration_rejected_by_diversity": 0, "exploration_rejected_by_quality": 0, "learning_probe_recent_win_rate": null, "learning_probe_recent_after_cost_pnl": 0, "learning_probe_recent_sample_count": 0, "learning_probe_quality_base_floor": 0.18, "learning_probe_quality_threshold": 0.18, "learning_probe_quality_threshold_effective": 0.18, "learning_probe_throttle_active": false, "learning_probe_throttle_reason": "", "recent_win_rate_throttle": false, "recent_pnl_throttle": false, "probes_shadowed_due_to_quality": 0, "probes_opened_due_to_quality": 0, "rejected_learning_probes_count": 0, "duplicate_market_blocked": 0, "duplicate_event_blocked": 0, "duplicate_cluster_blocked": 0, "weak_probe_throttled": 0, "top_rejected_near_misses": [], "opened_probe_explanations": [], "exploration_budget_used_usd": 0.0, "exploration_expected_loss_usd": 0.0, "exploration_pnl": 0, "exploration_counted_toward_readiness": false, "exploration_consumes_bregman_reserved_capacity": false, "top_learning_buckets": ["model_uncertain_high_liquidity", "chainlink_disagreement_case", "calibration_gap_bucket"], "category_coverage": {}, "cluster_diversity": {}, "avg_active_learning_score_selected": 0.282927, "avg_execution_quality_selected": 0.192353, "pending_feedback_count": 0, "completed_feedback_count": 0, "near_miss_examples": [{"market_id": "2556728", "event_id": "event:598778", "category": "uncategorized", "near_miss_reason": "confidence_below_exploration_floor", "failed_gate": "confidence_below_exploration_floor", "distance_to_threshold": null, "condition_needed_to_trade": "edge/confidence/EV above the soft tiny floor", "would_have_been_learning_bucket": "calibration_gap_bucket", "shadow_theoretical_edge": 0.0, "active_learning_score": 1.3444, "tick": 5}, {"market_id": "2553304", "event_id": "event:597987", "category": "uncategorized", "near_miss_reason": "stale_book", "failed_gate": "stale_book", "distance_to_threshold": 6.338714, "condition_needed_to_trade": "book age <= 20s", "would_have_been_learning_bucket": "model_uncertain_high_liquidity", "shadow_theoretical_edge": 0.0, "active_learning_score": -0.170168, "tick": 5}, {"market_id": "2071518", "event_id": "event:414457", "category": "uncategorized", "near_miss_reason": "stale_book", "failed_gate": "stale_book", "distance_to_threshold": 1.251244, "condition_needed_to_trade": "book age <= 20s", "would_have_been_learning_bucket": "model_uncertain_high_liquidity", "shadow_theoretical_edge": 0.0, "active_learning_score": 0.522982, "tick": 5}, {"market_id": "1130017", "event_id": "event:149589", "category": "uncategorized", "near_miss_reason": "stale_book", "failed_gate": "stale_book", "distance_to_threshold": 4.774189, "condition_needed_to_trade": "book age <= 20s", "would_have_been_learning_bucket": "chainlink_disagreement_case", "shadow_theoretical_edge": 0.0, "active_learning_score": 0.064582, "tick": 5}, {"market_id": "2553269", "event_id": "event:597985", "category": "uncategorized", "near_miss_reason": "stale_book", "failed_gate": "stale_book", "distance_to_threshold": 7.66627, "condition_needed_to_trade": "book age <= 20s", "would_have_been_learning_bucket": "chainlink_disagreement_case", "shadow_theoretical_edge": 0.0, "active_learning_score": 0.114582, "tick": 5}, {"market_id": "1897116", "event_id": "event:351742", "category": "uncategorized", "near_miss_reason": "stale_book", "failed_gate": "stale_book", "distance_to_threshold": 0.216726, "condition_needed_to_trade": "book age <= 20s", "would_have_been_learning_bucket": "calibration_gap_bucket", "shadow_theoretical_edge": 0.0, "active_learning_score": 1.064188, "tick": 5}, {"market_id": "2553341", "event_id": "event:597987", "category": "uncategorized", "near_miss_reason": "stale_book", "failed_gate": "stale_book", "distance_to_threshold": 8.277855, "condition_needed_to_trade": "book age <= 20s", "would_have_been_learning_bucket": "model_uncertain_high_liquidity", "shadow_theoretical_edge": 0.0, "active_learning_score": -0.160668, "tick": 5}, {"market_id": "2553413", "event_id": "event:597987", "category": "uncategorized", "near_miss_reason": "stale_book", "failed_gate": "stale_book", "distance_to_threshold": 5.85286, "condition_needed_to_trade": "book age <= 20s", "would_have_been_learning_bucket": "model_uncertain_high_liquidity", "shadow_theoretical_edge": 0.0, "active_learning_score": 0.124082, "tick": 5}, {"market_id": "616912", "event_id": "event:51456", "category": "uncategorized", "near_miss_reason": "stale_book", "failed_gate": "stale_book", "distance_to_threshold": 0.509112, "condition_needed_to_trade": "book age <= 20s", "would_have_been_learning_bucket": "chainlink_disagreement_case", "shadow_theoretical_edge": 0.0, "active_learning_score": 0.010582, "tick": 5}, {"market_id": "616911", "event_id": "event:51456", "category": "uncategorized", "near_miss_reason": "stale_book", "failed_gate": "stale_book", "distance_to_threshold": 0.216708, "condition_needed_to_trade": "book age <= 20s", "would_have_been_learning_bucket": "chainlink_disagreement_case", "shadow_theoretical_edge": 0.0, "active_learning_score": 0.095582, "tick": 5}], "active_learning_runtime_enabled": true, "active_learning_config_source": "aggressive_paper_profile", "active_learning_tiny_evaluator_called": 0, "active_learning_tiny_candidates_evaluated": 0, "active_learning_tiny_trades_selected": 0, "active_learning_tiny_trades_opened": 0, "active_learning_tiny_blocked_by_reason": {}, "active_learning_selected_but_not_evaluated_count": 0, "active_learning_config_mismatch": false, "active_learning_config_mismatch_reason": ""}