{"schema": "active_learning/1.0", "paper_only": true, "active_learning_enabled": true, "random_exploration_enabled": false, "random_exploration_opened_trades": 0, "legacy_random_exploration_blocked": 605, "active_learning_candidates_considered": 9130, "active_learning_candidates_selected": 9155, "active_learning_shadow_selected": 9062, "zero_selection_reason": null, "exploration_trades_opened": 15, "exploration_shadow_only": 992, "exploration_rejected_by_realism": 204, "exploration_rejected_by_profitability": 0, "exploration_rejected_by_budget": 96, "exploration_rejected_by_collision": 0, "exploration_rejected_by_diversity": 0, "exploration_budget_used_usd": 15.0, "exploration_expected_loss_usd": 0.123, "exploration_pnl": -0.8963, "exploration_counted_toward_readiness": false, "exploration_consumes_bregman_reserved_capacity": false, "top_learning_buckets": ["category_under_sampled", "calibration_gap_bucket"], "category_coverage": {"uncategorized": 93}, "cluster_diversity": {"event:31875": 6, "event:585449": 6, "event:179312": 1, "event:45915": 8, "event:79987": 14, "event:591201": 4, "event:591159": 1, "event:90177": 7, "event:57711": 5, "event:573076": 1, "event:106884": 8, "event:448037": 1, "event:52166": 7, "event:351744": 4, "event:591825": 7, "event:351735": 7, "event:48978": 6}, "avg_active_learning_score_selected": 1.018566, "avg_execution_quality_selected": 0.19076, "pending_feedback_count": 0, "completed_feedback_count": 15, "near_miss_examples": [{"market_id": "2546685", "event_id": "event:595486", "category": "uncategorized", "near_miss_reason": "stale_book", "failed_gate": "stale_book", "distance_to_threshold": 3.905216, "condition_needed_to_trade": "book age <= 20s", "would_have_been_learning_bucket": "category_under_sampled", "shadow_theoretical_edge": 0.0, "active_learning_score": 0.91085, "tick": 78}, {"market_id": "2069655", "event_id": "event:413862", "category": "uncategorized", "near_miss_reason": "confidence_below_exploration_floor", "failed_gate": "confidence_below_exploration_floor", "distance_to_threshold": null, "condition_needed_to_trade": "edge/confidence/EV above the soft tiny floor", "would_have_been_learning_bucket": "category_under_sampled", "shadow_theoretical_edge": 0.0, "active_learning_score": 0.87509, "tick": 79}, {"market_id": "2549223", "event_id": "event:596301", "category": "uncategorized", "near_miss_reason": "stale_book", "failed_gate": "stale_book", "distance_to_threshold": 3.260938, "condition_needed_to_trade": "book age <= 20s", "would_have_been_learning_bucket": "category_under_sampled", "shadow_theoretical_edge": 0.0, "active_learning_score": 0.64809, "tick": 79}, {"market_id": "2410603", "event_id": "event:548276", "category": "uncategorized", "near_miss_reason": "confidence_below_exploration_floor", "failed_gate": "confidence_below_exploration_floor", "distance_to_threshold": null, "condition_needed_to_trade": "edge/confidence/EV above the soft tiny floor", "would_have_been_learning_bucket": "category_under_sampled", "shadow_theoretical_edge": 0.0, "active_learning_score": 0.83659, "tick": 79}, {"market_id": "906974", "event_id": "event:101772", "category": "uncategorized", "near_miss_reason": "stale_book", "failed_gate": "stale_book", "distance_to_threshold": 6.813224, "condition_needed_to_trade": "book age <= 20s", "would_have_been_learning_bucket": "calibration_gap_bucket", "shadow_theoretical_edge": 0.0, "active_learning_score": 1.81825, "tick": 79}, {"market_id": "562832", "event_id": "event:32228", "category": "uncategorized", "near_miss_reason": "confidence_below_exploration_floor", "failed_gate": "confidence_below_exploration_floor", "distance_to_threshold": null, "condition_needed_to_trade": "edge/confidence/EV above the soft tiny floor", "would_have_been_learning_bucket": "category_under_sampled", "shadow_theoretical_edge": 0.0, "active_learning_score": 0.85934, "tick": 79}, {"market_id": "1357397", "event_id": "event:202857", "category": "uncategorized", "near_miss_reason": "confidence_below_exploration_floor", "failed_gate": "confidence_below_exploration_floor", "distance_to_threshold": null, "condition_needed_to_trade": "edge/confidence/EV above the soft tiny floor", "would_have_been_learning_bucket": "category_under_sampled", "shadow_theoretical_edge": 0.0, "active_learning_score": 0.83009, "tick": 79}, {"market_id": "2528041", "event_id": "event:589435", "category": "uncategorized", "near_miss_reason": "stale_book", "failed_gate": "stale_book", "distance_to_threshold": 4.464153, "condition_needed_to_trade": "book age <= 20s", "would_have_been_learning_bucket": "category_under_sampled", "shadow_theoretical_edge": 0.0, "active_learning_score": 0.86609, "tick": 79}, {"market_id": "2491378", "event_id": "event:580294", "category": "uncategorized", "near_miss_reason": "confidence_below_exploration_floor", "failed_gate": "confidence_below_exploration_floor", "distance_to_threshold": null, "condition_needed_to_trade": "edge/confidence/EV above the soft tiny floor", "would_have_been_learning_bucket": "category_under_sampled", "shadow_theoretical_edge": 0.0, "active_learning_score": 0.88509, "tick": 79}, {"market_id": "2546685", "event_id": "event:595486", "category": "uncategorized", "near_miss_reason": "stale_book", "failed_gate": "stale_book", "distance_to_threshold": 3.905216, "condition_needed_to_trade": "book age <= 20s", "would_have_been_learning_bucket": "category_under_sampled", "shadow_theoretical_edge": 0.0, "active_learning_score": 0.91085, "tick": 79}], "active_learning_runtime_enabled": true, "active_learning_config_source": "aggressive_paper_profile", "active_learning_tiny_evaluator_called": 93, "active_learning_tiny_candidates_evaluated": 93, "active_learning_tiny_trades_selected": 93, "active_learning_tiny_trades_opened": 15, "active_learning_tiny_blocked_by_reason": {"collision_blocked": 53, "exploration_budget_exhausted": 25}, "active_learning_selected_but_not_evaluated_count": 0, "active_learning_config_mismatch": false, "active_learning_config_mismatch_reason": ""}